[
  {
    "type": "tab.updated",
    "details": {
      "params": {
        "0": 2,
        "1": {
          "status": "complete"
        },
        "2": {
          "active": true,
          "audible": false,
          "autoDiscardable": true,
          "discarded": false,
          "favIconUrl": "",
          "height": 838,
          "highlighted": true,
          "id": 2,
          "incognito": false,
          "index": 0,
          "mutedInfo": {
            "muted": false
          },
          "pinned": false,
          "selected": true,
          "status": "complete",
          "title": "Save",
          "url": "chrome-extension://ikfgdchohmenjhbbpbnknidjagelhjma/command.html?save",
          "width": 935,
          "windowId": 1
        }
      },
      "timeStamp": 1502703979776
    }
  },
  {
    "type": "download.created",
    "details": {
      "params": {
        "0": {
          "bytesReceived": 0,
          "canResume": false,
          "danger": "safe",
          "exists": true,
          "fileSize": 133271,
          "filename": "",
          "finalUrl": "blob:chrome-extension://ikfgdchohmenjhbbpbnknidjagelhjma/1a9ee3a1-b31e-4daf-9876-0a32a51b3a29",
          "id": 40,
          "incognito": false,
          "mime": "text/json",
          "paused": false,
          "referrer": "",
          "startTime": "2017-08-14T09:46:19.779Z",
          "state": "in_progress",
          "totalBytes": 133271,
          "url": "blob:chrome-extension://ikfgdchohmenjhbbpbnknidjagelhjma/1a9ee3a1-b31e-4daf-9876-0a32a51b3a29"
        }
      },
      "timeStamp": 1502703979780
    }
  },
  {
    "type": "download.determiningFilename",
    "details": {
      "params": {
        "0": {
          "bytesReceived": 0,
          "canResume": false,
          "danger": "safe",
          "exists": true,
          "fileSize": 133271,
          "filename": "ECAP_G_2017-08-14T09-46-19.760Z.json",
          "finalUrl": "blob:chrome-extension://ikfgdchohmenjhbbpbnknidjagelhjma/1a9ee3a1-b31e-4daf-9876-0a32a51b3a29",
          "id": 40,
          "incognito": false,
          "mime": "text/json",
          "paused": false,
          "referrer": "",
          "startTime": "2017-08-14T09:46:19.779Z",
          "state": "in_progress",
          "totalBytes": 133271,
          "url": "blob:chrome-extension://ikfgdchohmenjhbbpbnknidjagelhjma/1a9ee3a1-b31e-4daf-9876-0a32a51b3a29"
        }
      },
      "timeStamp": 1502703979782
    }
  },
  {
    "type": "download.changed",
    "details": {
      "params": {
        "0": {
          "filename": {
            "current": "./json/ECAP_G_2017-08-14T09-46-19.760Z.json",
            "previous": ""
          },
          "id": 40
        }
      },
      "timeStamp": 1502703979791
    }
  },
  {
    "type": "download.changed",
    "details": {
      "params": {
        "0": {
          "endTime": {
            "current": "2017-08-14T09:46:19.793Z"
          },
          "id": 40,
          "state": {
            "current": "complete",
            "previous": "in_progress"
          }
        }
      },
      "timeStamp": 1502703979793
    }
  },
  {
    "type": "response",
    "details": {
      "frameId": -1,
      "method": "GET",
      "parentFrameId": -1,
      "requestId": "3879",
      "responseHeaders": [
        {
          "name": "Access-Control-Allow-Headers",
          "value": "Origin, X-Requested-With, Content-Type, Accept"
        },
        {
          "name": "Access-Control-Allow-Methods",
          "value": "GET,PUT,POST,DELETE"
        },
        {
          "name": "Access-Control-Allow-Origin",
          "value": "*"
        },
        {
          "name": "Content-Type",
          "value": "image/gif"
        },
        {
          "name": "Date",
          "value": "Mon, 14 Aug 2017 09:46:19 GMT"
        },
        {
          "name": "X-Powered-By",
          "value": "Express"
        },
        {
          "name": "Content-Length",
          "value": "70"
        },
        {
          "name": "Connection",
          "value": "keep-alive"
        }
      ],
      "statusCode": 200,
      "statusLine": "HTTP/1.1 200 OK",
      "tabId": -1,
      "type": "ping",
      "url": "http://dt.spamanalyst.com/ptmd?t=%7B%22status%22%3A31%2C%22za%22%3A1%2C%22aa%22%3A%22Mozilla%2F5.0%20(X11%3B%20Linux%20x86_64)%20AppleWebKit%2F537.36%20(KHTML%2C%20like%20Gecko)%20Chrome%2F60.0.3112.90%20Safari%2F537.36%22%2C%22env%22%3A%22p%22%2C%22gh%22%3A%2215027039770262489559179%22%2C%22ts%22%3A%221429807462558%22%2C%22vs%22%3A%226.0.81%22%2C%22al%22%3A10%2C%22fc%22%3A-1%2C%22ea%22%3A%229e5d75d0-809f-11e7-a80a-3fa6648c3f60%22%2C%22eti%22%3A1502703976%2C%22slst%22%3A%221502703977018%22%2C%22lf%22%3A1%2C%22part_id%22%3A%225PAMARTA%22%2C%22cust_id%22%3A%229CUO250V9%22%2C%22gc%22%3A1502703979740%2C%22es%22%3A31%2C%22rb%22%3A%5B%7B%22ele%22%3A%22BODY%22%2C%22ti%22%3A2721%7D%5D%2C%22xk%22%3A%22230%22%2C%22xt%22%3A%221%22%2C%22xlb%22%3A1%2C%22xlc%22%3A1%2C%22fpgt%22%3A-1%2C%22pac%22%3A1%7D",
      "id": 4030,
      "contextId": -1,
      "parentContextId": -1,
      "windowId": -1,
      "start": 1502703979821,
      "end": 1502703979821,
      "fromCache": false,
      "ip": "52.86.81.28"
    }
  },
  {
    "type": "response",
    "details": {
      "frameId": -1,
      "method": "GET",
      "parentFrameId": -1,
      "requestId": "3880",
      "responseHeaders": [
        {
          "name": "Access-Control-Allow-Headers",
          "value": "Origin, X-Requested-With, Content-Type, Accept"
        },
        {
          "name": "Access-Control-Allow-Methods",
          "value": "GET,PUT,POST,DELETE"
        },
        {
          "name": "Access-Control-Allow-Origin",
          "value": "*"
        },
        {
          "name": "Content-Type",
          "value": "image/gif"
        },
        {
          "name": "Date",
          "value": "Mon, 14 Aug 2017 09:46:19 GMT"
        },
        {
          "name": "X-Powered-By",
          "value": "Express"
        },
        {
          "name": "Content-Length",
          "value": "70"
        },
        {
          "name": "Connection",
          "value": "keep-alive"
        }
      ],
      "statusCode": 200,
      "statusLine": "HTTP/1.1 200 OK",
      "tabId": -1,
      "type": "ping",
      "url": "http://dt.spamanalyst.com/ptmd?t=%7B%22pet%22%3A2721%2C%22exInd%22%3A22%2C%22status%22%3A22%2C%22za%22%3A1%2C%22aa%22%3A%22Mozilla%2F5.0%20(X11%3B%20Linux%20x86_64)%20AppleWebKit%2F537.36%20(KHTML%2C%20like%20Gecko)%20Chrome%2F60.0.3112.90%20Safari%2F537.36%22%2C%22env%22%3A%22p%22%2C%22gh%22%3A%2215027039770262489559179%22%2C%22ts%22%3A%221429807462558%22%2C%22vs%22%3A%226.0.81%22%2C%22al%22%3A10%2C%22fc%22%3A-1%2C%22ea%22%3A%229e5d75d0-809f-11e7-a80a-3fa6648c3f60%22%2C%22eti%22%3A1502703976%2C%22slst%22%3A%221502703977018%22%2C%22lf%22%3A1%2C%22part_id%22%3A%225PAMARTA%22%2C%22cust_id%22%3A%229CUO250V9%22%2C%22gc%22%3A1502703979740%2C%22es%22%3A22%2C%22lUrl%22%3A%22http%3A%2F%2Ffindbetterresults.com%2F%3Fdn%3Debookshare.net%26pid%3D9PO755G95%22%7D",
      "id": 4031,
      "contextId": -1,
      "parentContextId": -1,
      "windowId": -1,
      "start": 1502703979821,
      "end": 1502703979822,
      "fromCache": false,
      "ip": "52.86.81.28"
    }
  },
  {
    "type": "response",
    "details": {
      "frameId": -1,
      "method": "GET",
      "parentFrameId": -1,
      "requestId": "3878",
      "responseHeaders": [
        {
          "name": "Access-Control-Allow-Headers",
          "value": "Origin, X-Requested-With, Content-Type, Accept"
        },
        {
          "name": "Access-Control-Allow-Methods",
          "value": "GET,PUT,POST,DELETE"
        },
        {
          "name": "Access-Control-Allow-Origin",
          "value": "*"
        },
        {
          "name": "Content-Type",
          "value": "image/gif"
        },
        {
          "name": "Date",
          "value": "Mon, 14 Aug 2017 09:46:19 GMT"
        },
        {
          "name": "X-Powered-By",
          "value": "Express"
        },
        {
          "name": "Content-Length",
          "value": "70"
        },
        {
          "name": "Connection",
          "value": "keep-alive"
        }
      ],
      "statusCode": 200,
      "statusLine": "HTTP/1.1 200 OK",
      "tabId": -1,
      "type": "ping",
      "url": "http://dt.spamanalyst.com/ptmd?t=%7B%22pet%22%3A2721%2C%22exInd%22%3A23%2C%22status%22%3A23%2C%22za%22%3A1%2C%22aa%22%3A%22Mozilla%2F5.0%20(X11%3B%20Linux%20x86_64)%20AppleWebKit%2F537.36%20(KHTML%2C%20like%20Gecko)%20Chrome%2F60.0.3112.90%20Safari%2F537.36%22%2C%22env%22%3A%22p%22%2C%22gh%22%3A%2215027039770262489559179%22%2C%22ts%22%3A%221429807462558%22%2C%22vs%22%3A%226.0.81%22%2C%22al%22%3A10%2C%22fc%22%3A-1%2C%22ea%22%3A%229e5d75d0-809f-11e7-a80a-3fa6648c3f60%22%2C%22eti%22%3A1502703976%2C%22slst%22%3A%221502703977018%22%2C%22lf%22%3A1%2C%22part_id%22%3A%225PAMARTA%22%2C%22cust_id%22%3A%229CUO250V9%22%2C%22gc%22%3A1502703979739%2C%22es%22%3A23%7D",
      "id": 4029,
      "contextId": -1,
      "parentContextId": -1,
      "windowId": -1,
      "start": 1502703979822,
      "end": 1502703979822,
      "fromCache": false,
      "ip": "52.86.81.28"
    }
  },
  {
    "type": "navigation.beforeNavigate",
    "details": {
      "frameId": 0,
      "parentFrameId": -1,
      "processId": -1,
      "tabId": 2,
      "timeStamp": 1502703981817,
      "url": "http://www.ebookee.com/",
      "windowId": 1
    }
  },
  {
    "type": "request",
    "details": {
      "frameId": 0,
      "method": "GET",
      "parentFrameId": -1,
      "requestId": "3884",
      "tabId": 2,
      "type": "main_frame",
      "url": "http://www.ebookee.com/",
      "id": 4034,
      "contextId": 325,
      "parentContextId": -1,
      "windowId": 1,
      "start": 1502703981817,
      "end": 1502703981818,
      "requestHeaders": [
        {
          "name": "Upgrade-Insecure-Requests",
          "value": "1"
        },
        {
          "name": "User-Agent",
          "value": "Mozilla/5.0 (X11; Linux x86_64) AppleWebKit/537.36 (KHTML, like Gecko) Chrome/60.0.3112.90 Safari/537.36"
        },
        {
          "name": "Accept",
          "value": "text/html,application/xhtml+xml,application/xml;q=0.9,image/webp,image/apng,*/*;q=0.8"
        },
        {
          "name": "Accept-Encoding",
          "value": "gzip, deflate"
        },
        {
          "name": "Accept-Language",
          "value": "en-GB,en-US;q=0.8,en;q=0.6"
        }
      ]
    }
  },
  {
    "type": "response",
    "details": {
      "frameId": 0,
      "method": "GET",
      "parentFrameId": -1,
      "requestId": "3884",
      "responseHeaders": [
        {
          "name": "Server",
          "value": "nginx"
        },
        {
          "name": "Date",
          "value": "Mon, 14 Aug 2017 09:46:21 GMT"
        },
        {
          "name": "Content-Type",
          "value": "text/html"
        },
        {
          "name": "Content-Length",
          "value": "178"
        },
        {
          "name": "Connection",
          "value": "close"
        },
        {
          "name": "Location",
          "value": "https://ebookee.org/"
        }
      ],
      "statusCode": 301,
      "statusLine": "HTTP/1.1 301 Moved Permanently",
      "tabId": 2,
      "type": "main_frame",
      "url": "http://www.ebookee.com/",
      "id": 4034,
      "contextId": 325,
      "parentContextId": -1,
      "windowId": 1,
      "start": 1502703981841,
      "end": 1502703981843,
      "fromCache": false,
      "ip": "185.7.34.123",
      "redirectUrl": "https://ebookee.org/"
    }
  },
  {
    "type": "request",
    "details": {
      "frameId": 0,
      "method": "GET",
      "parentFrameId": -1,
      "requestId": "3884",
      "tabId": 2,
      "type": "main_frame",
      "url": "https://ebookee.org/",
      "id": 4035,
      "contextId": 326,
      "parentContextId": -1,
      "windowId": 1,
      "start": 1502703981843,
      "end": 1502703981843,
      "requestHeaders": [
        {
          "name": "Upgrade-Insecure-Requests",
          "value": "1"
        },
        {
          "name": "User-Agent",
          "value": "Mozilla/5.0 (X11; Linux x86_64) AppleWebKit/537.36 (KHTML, like Gecko) Chrome/60.0.3112.90 Safari/537.36"
        },
        {
          "name": "Accept",
          "value": "text/html,application/xhtml+xml,application/xml;q=0.9,image/webp,image/apng,*/*;q=0.8"
        },
        {
          "name": "Accept-Encoding",
          "value": "gzip, deflate, br"
        },
        {
          "name": "Accept-Language",
          "value": "en-GB,en-US;q=0.8,en;q=0.6"
        }
      ]
    }
  },
  {
    "type": "cookie.changed",
    "details": {
      "cause": "set_cookie",
      "cookie": {
        "domain": ".ebookee.org",
        "expirationDate": "1502703982864000",
        "hostOnly": false,
        "httpOnly": false,
        "name": "vs",
        "path": "/",
        "sameSite": "no_restriction",
        "secure": false,
        "session": false,
        "storeId": -1,
        "value": "0"
      },
      "removed": false,
      "timeStamp": 1502703982102,
      "tabId": 2,
      "windowId": 1,
      "frameId": 0,
      "contextId": 326
    }
  },
  {
    "type": "variable.new",
    "details": {
      "name": "vs",
      "type": "cookie",
      "value": "0",
      "timeStamp": 1502703982102,
      "tabId": 2,
      "windowId": 1,
      "frameId": 0,
      "contextId": 326
    }
  },
  {
    "type": "cookie.changed",
    "details": {
      "cause": "explicit",
      "cookie": {
        "domain": ".ebookee.org",
        "expirationDate": 1503567982.102083,
        "hostOnly": false,
        "httpOnly": false,
        "name": "vs",
        "path": "/",
        "sameSite": "no_restriction",
        "secure": false,
        "session": false,
        "storeId": "0",
        "value": "0"
      },
      "removed": false,
      "timeStamp": 1502703982104
    }
  },
  {
    "type": "variable.new",
    "details": {
      "name": "vs",
      "type": "cookie",
      "value": "0",
      "timeStamp": 1502703982104
    }
  },
  {
    "type": "response",
    "details": {
      "frameId": 0,
      "method": "GET",
      "parentFrameId": -1,
      "requestId": "3884",
      "responseHeaders": [
        {
          "name": "status",
          "value": "200"
        },
        {
          "name": "server",
          "value": "nginx"
        },
        {
          "name": "date",
          "value": "Mon, 14 Aug 2017 09:46:22 GMT"
        },
        {
          "name": "content-type",
          "value": "text/html; charset=UTF-8"
        },
        {
          "name": "vary",
          "value": "Accept-Encoding"
        },
        {
          "name": "set-cookie",
          "value": "vs=0; expires=Thu, 24-Aug-2017 09:46:22 GMT; Max-Age=864000; path=/; domain=.ebookee.org"
        },
        {
          "name": "content-encoding",
          "value": "gzip"
        }
      ],
      "statusCode": 200,
      "statusLine": "HTTP/1.1 200",
      "tabId": 2,
      "type": "main_frame",
      "url": "https://ebookee.org/",
      "id": 4035,
      "contextId": 326,
      "parentContextId": -1,
      "windowId": 1,
      "start": 1502703982102,
      "end": 1502703982108,
      "fromCache": false,
      "ip": "185.7.34.123"
    }
  },
  {
    "type": "tab.updated",
    "details": {
      "params": {
        "0": 2,
        "1": {
          "status": "loading",
          "url": "https://ebookee.org/"
        },
        "2": {
          "active": true,
          "audible": false,
          "autoDiscardable": true,
          "discarded": false,
          "height": 838,
          "highlighted": true,
          "id": 2,
          "incognito": false,
          "index": 0,
          "mutedInfo": {
            "muted": false
          },
          "pinned": false,
          "selected": true,
          "status": "loading",
          "title": "https://ebookee.org",
          "url": "https://ebookee.org/",
          "width": 935,
          "windowId": 1
        }
      },
      "timeStamp": 1502703982113
    }
  },
  {
    "type": "tab.zoomChange",
    "details": {
      "params": {
        "0": {
          "newZoomFactor": 1,
          "oldZoomFactor": 1,
          "tabId": 2,
          "zoomSettings": {
            "mode": "automatic",
            "scope": "per-origin"
          }
        }
      },
      "timeStamp": 1502703982113
    }
  },
  {
    "type": "navigation.committed",
    "details": {
      "frameId": 0,
      "processId": 47,
      "tabId": 2,
      "timeStamp": 1502703982114,
      "transitionQualifiers": [
        "server_redirect"
      ],
      "transitionType": "typed",
      "url": "https://ebookee.org/",
      "windowId": 1
    }
  },
  {
    "type": "download.visited",
    "details": {
      "params": {
        "0": {
          "id": "70",
          "lastVisitTime": 1502703982109.822,
          "title": "",
          "typedCount": 1,
          "url": "http://www.ebookee.com/",
          "visitCount": 1
        }
      },
      "timeStamp": 1502703982143
    }
  },
  {
    "type": "download.visited",
    "details": {
      "params": {
        "0": {
          "id": "71",
          "lastVisitTime": 1502703982109.822,
          "title": "",
          "typedCount": 0,
          "url": "https://ebookee.org/",
          "visitCount": 1
        }
      },
      "timeStamp": 1502703982143
    }
  },
  {
    "type": "request",
    "details": {
      "frameId": 0,
      "method": "GET",
      "parentFrameId": -1,
      "requestId": "3885",
      "tabId": 2,
      "type": "stylesheet",
      "url": "https://ebookee.org/css/main.min.css?20170220",
      "id": 4036,
      "contextId": 326,
      "parentContextId": -1,
      "windowId": 1,
      "start": 1502703982143,
      "end": 1502703982144,
      "requestHeaders": [
        {
          "name": "User-Agent",
          "value": "Mozilla/5.0 (X11; Linux x86_64) AppleWebKit/537.36 (KHTML, like Gecko) Chrome/60.0.3112.90 Safari/537.36"
        },
        {
          "name": "Accept",
          "value": "text/css,*/*;q=0.1"
        },
        {
          "name": "Referer",
          "value": "https://ebookee.org/"
        },
        {
          "name": "Accept-Encoding",
          "value": "gzip, deflate, br"
        },
        {
          "name": "Accept-Language",
          "value": "en-GB,en-US;q=0.8,en;q=0.6"
        },
        {
          "name": "Cookie",
          "value": "vs=0"
        }
      ]
    }
  },
  {
    "type": "request",
    "details": {
      "frameId": 0,
      "method": "GET",
      "parentFrameId": -1,
      "requestId": "3886",
      "tabId": 2,
      "type": "image",
      "url": "https://ebookee.org/img/ebookee2.png",
      "id": 4037,
      "contextId": 326,
      "parentContextId": -1,
      "windowId": 1,
      "start": 1502703982144,
      "end": 1502703982144,
      "requestHeaders": [
        {
          "name": "User-Agent",
          "value": "Mozilla/5.0 (X11; Linux x86_64) AppleWebKit/537.36 (KHTML, like Gecko) Chrome/60.0.3112.90 Safari/537.36"
        },
        {
          "name": "Accept",
          "value": "image/webp,image/apng,image/*,*/*;q=0.8"
        },
        {
          "name": "Referer",
          "value": "https://ebookee.org/"
        },
        {
          "name": "Accept-Encoding",
          "value": "gzip, deflate, br"
        },
        {
          "name": "Accept-Language",
          "value": "en-GB,en-US;q=0.8,en;q=0.6"
        },
        {
          "name": "Cookie",
          "value": "vs=0"
        }
      ]
    }
  },
  {
    "type": "tab.updated",
    "details": {
      "params": {
        "0": 2,
        "1": {
          "title": "Ebookee: Free Download eBooks Search Engine!"
        },
        "2": {
          "active": true,
          "audible": false,
          "autoDiscardable": true,
          "discarded": false,
          "height": 838,
          "highlighted": true,
          "id": 2,
          "incognito": false,
          "index": 0,
          "mutedInfo": {
            "muted": false
          },
          "pinned": false,
          "selected": true,
          "status": "loading",
          "title": "Ebookee: Free Download eBooks Search Engine!",
          "url": "https://ebookee.org/",
          "width": 935,
          "windowId": 1
        }
      },
      "timeStamp": 1502703982145
    }
  },
  {
    "type": "response",
    "details": {
      "frameId": 0,
      "method": "GET",
      "parentFrameId": -1,
      "requestId": "3885",
      "responseHeaders": [
        {
          "name": "status",
          "value": "200"
        },
        {
          "name": "server",
          "value": "nginx"
        },
        {
          "name": "date",
          "value": "Mon, 14 Aug 2017 09:46:22 GMT"
        },
        {
          "name": "content-type",
          "value": "text/css"
        },
        {
          "name": "last-modified",
          "value": "Sun, 19 Feb 2017 16:36:24 GMT"
        },
        {
          "name": "vary",
          "value": "Accept-Encoding"
        },
        {
          "name": "etag",
          "value": "W/\"58a9c988-381d\""
        },
        {
          "name": "expires",
          "value": "Wed, 13 Sep 2017 09:46:22 GMT"
        },
        {
          "name": "cache-control",
          "value": "max-age=2592000"
        },
        {
          "name": "content-encoding",
          "value": "gzip"
        }
      ],
      "statusCode": 200,
      "statusLine": "HTTP/1.1 200",
      "tabId": 2,
      "type": "stylesheet",
      "url": "https://ebookee.org/css/main.min.css?20170220",
      "id": 4036,
      "contextId": 326,
      "parentContextId": -1,
      "windowId": 1,
      "start": 1502703982146,
      "end": 1502703982147,
      "fromCache": false,
      "ip": "185.7.34.123"
    }
  },
  {
    "type": "response",
    "details": {
      "frameId": 0,
      "method": "GET",
      "parentFrameId": -1,
      "requestId": "3886",
      "responseHeaders": [
        {
          "name": "status",
          "value": "200"
        },
        {
          "name": "server",
          "value": "nginx"
        },
        {
          "name": "date",
          "value": "Mon, 14 Aug 2017 09:46:22 GMT"
        },
        {
          "name": "content-type",
          "value": "image/png"
        },
        {
          "name": "content-length",
          "value": "1378"
        },
        {
          "name": "last-modified",
          "value": "Sun, 01 May 2016 05:07:14 GMT"
        },
        {
          "name": "etag",
          "value": "\"57258f02-562\""
        },
        {
          "name": "expires",
          "value": "Wed, 13 Sep 2017 09:46:22 GMT"
        },
        {
          "name": "cache-control",
          "value": "max-age=2592000"
        },
        {
          "name": "accept-ranges",
          "value": "bytes"
        }
      ],
      "statusCode": 200,
      "statusLine": "HTTP/1.1 200",
      "tabId": 2,
      "type": "image",
      "url": "https://ebookee.org/img/ebookee2.png",
      "id": 4037,
      "contextId": 326,
      "parentContextId": -1,
      "windowId": 1,
      "start": 1502703982147,
      "end": 1502703982147,
      "fromCache": false,
      "ip": "185.7.34.123"
    }
  },
  {
    "type": "request",
    "details": {
      "frameId": 0,
      "method": "GET",
      "parentFrameId": -1,
      "requestId": "3890",
      "tabId": 2,
      "type": "script",
      "url": "https://i.po.st/static/v3/post-widget.js#publisherKey=https://ebookee.org-498",
      "id": 4038,
      "contextId": 326,
      "parentContextId": -1,
      "windowId": 1,
      "start": 1502703982148,
      "end": 1502703982148,
      "requestHeaders": [
        {
          "name": "User-Agent",
          "value": "Mozilla/5.0 (X11; Linux x86_64) AppleWebKit/537.36 (KHTML, like Gecko) Chrome/60.0.3112.90 Safari/537.36"
        },
        {
          "name": "Accept",
          "value": "*/*"
        },
        {
          "name": "Referer",
          "value": "https://ebookee.org/"
        },
        {
          "name": "Accept-Encoding",
          "value": "gzip, deflate, br"
        },
        {
          "name": "Accept-Language",
          "value": "en-GB,en-US;q=0.8,en;q=0.6"
        },
        {
          "name": "Cookie",
          "value": "post_dcm=17392; post_uuid=27919174-8174-4091-a6a8-95b9da1c898f"
        }
      ]
    }
  },
  {
    "type": "request",
    "details": {
      "frameId": 0,
      "method": "GET",
      "parentFrameId": -1,
      "requestId": "3887",
      "tabId": 2,
      "type": "image",
      "url": "https://ebookee.org/img/search.gif",
      "id": 4039,
      "contextId": 326,
      "parentContextId": -1,
      "windowId": 1,
      "start": 1502703982148,
      "end": 1502703982148,
      "requestHeaders": [
        {
          "name": "User-Agent",
          "value": "Mozilla/5.0 (X11; Linux x86_64) AppleWebKit/537.36 (KHTML, like Gecko) Chrome/60.0.3112.90 Safari/537.36"
        },
        {
          "name": "Accept",
          "value": "image/webp,image/apng,image/*,*/*;q=0.8"
        },
        {
          "name": "Referer",
          "value": "https://ebookee.org/"
        },
        {
          "name": "Accept-Encoding",
          "value": "gzip, deflate, br"
        },
        {
          "name": "Accept-Language",
          "value": "en-GB,en-US;q=0.8,en;q=0.6"
        },
        {
          "name": "Cookie",
          "value": "vs=0"
        }
      ]
    }
  },
  {
    "type": "request",
    "details": {
      "frameId": 0,
      "method": "GET",
      "parentFrameId": -1,
      "requestId": "3888",
      "tabId": 2,
      "type": "image",
      "url": "https://ebookee.org/img/sb.png",
      "id": 4040,
      "contextId": 326,
      "parentContextId": -1,
      "windowId": 1,
      "start": 1502703982148,
      "end": 1502703982149,
      "requestHeaders": [
        {
          "name": "User-Agent",
          "value": "Mozilla/5.0 (X11; Linux x86_64) AppleWebKit/537.36 (KHTML, like Gecko) Chrome/60.0.3112.90 Safari/537.36"
        },
        {
          "name": "Accept",
          "value": "image/webp,image/apng,image/*,*/*;q=0.8"
        },
        {
          "name": "Referer",
          "value": "https://ebookee.org/"
        },
        {
          "name": "Accept-Encoding",
          "value": "gzip, deflate, br"
        },
        {
          "name": "Accept-Language",
          "value": "en-GB,en-US;q=0.8,en;q=0.6"
        },
        {
          "name": "Cookie",
          "value": "vs=0"
        }
      ]
    }
  },
  {
    "type": "request",
    "details": {
      "frameId": 0,
      "method": "GET",
      "parentFrameId": -1,
      "requestId": "3889",
      "tabId": 2,
      "type": "image",
      "url": "https://ebookee.org/img/gotop.gif",
      "id": 4041,
      "contextId": 326,
      "parentContextId": -1,
      "windowId": 1,
      "start": 1502703982149,
      "end": 1502703982149,
      "requestHeaders": [
        {
          "name": "User-Agent",
          "value": "Mozilla/5.0 (X11; Linux x86_64) AppleWebKit/537.36 (KHTML, like Gecko) Chrome/60.0.3112.90 Safari/537.36"
        },
        {
          "name": "Accept",
          "value": "image/webp,image/apng,image/*,*/*;q=0.8"
        },
        {
          "name": "Referer",
          "value": "https://ebookee.org/"
        },
        {
          "name": "Accept-Encoding",
          "value": "gzip, deflate, br"
        },
        {
          "name": "Accept-Language",
          "value": "en-GB,en-US;q=0.8,en;q=0.6"
        },
        {
          "name": "Cookie",
          "value": "vs=0"
        }
      ]
    }
  },
  {
    "type": "request",
    "details": {
      "frameId": 0,
      "method": "GET",
      "parentFrameId": -1,
      "requestId": "3891",
      "tabId": 2,
      "type": "script",
      "url": "https://ssl.google-analytics.com/ga.js",
      "id": 4042,
      "contextId": 326,
      "parentContextId": -1,
      "windowId": 1,
      "start": 1502703982149,
      "end": 1502703982149,
      "requestHeaders": [
        {
          "name": "User-Agent",
          "value": "Mozilla/5.0 (X11; Linux x86_64) AppleWebKit/537.36 (KHTML, like Gecko) Chrome/60.0.3112.90 Safari/537.36"
        },
        {
          "name": "Accept",
          "value": "*/*"
        },
        {
          "name": "Referer",
          "value": "https://ebookee.org/"
        },
        {
          "name": "Accept-Encoding",
          "value": "gzip, deflate, br"
        },
        {
          "name": "Accept-Language",
          "value": "en-GB,en-US;q=0.8,en;q=0.6"
        }
      ]
    }
  },
  {
    "type": "response",
    "details": {
      "frameId": 0,
      "method": "GET",
      "parentFrameId": -1,
      "requestId": "3891",
      "responseHeaders": [
        {
          "name": "status",
          "value": "200"
        },
        {
          "name": "timing-allow-origin",
          "value": "*"
        },
        {
          "name": "date",
          "value": "Mon, 14 Aug 2017 08:40:02 GMT"
        },
        {
          "name": "expires",
          "value": "Mon, 14 Aug 2017 10:40:02 GMT"
        },
        {
          "name": "last-modified",
          "value": "Tue, 01 Aug 2017 03:25:32 GMT"
        },
        {
          "name": "x-content-type-options",
          "value": "nosniff"
        },
        {
          "name": "content-type",
          "value": "text/javascript"
        },
        {
          "name": "vary",
          "value": "Accept-Encoding"
        },
        {
          "name": "content-encoding",
          "value": "gzip"
        },
        {
          "name": "server",
          "value": "Golfe2"
        },
        {
          "name": "content-length",
          "value": "16022"
        },
        {
          "name": "cache-control",
          "value": "public, max-age=7200"
        },
        {
          "name": "age",
          "value": "3580"
        },
        {
          "name": "alt-svc",
          "value": "quic=\":443\"; ma=2592000; v=\"39,38,37,35\""
        }
      ],
      "statusCode": 200,
      "statusLine": "HTTP/1.1 200",
      "tabId": 2,
      "type": "script",
      "url": "https://ssl.google-analytics.com/ga.js",
      "id": 4042,
      "contextId": 326,
      "parentContextId": -1,
      "windowId": 1,
      "start": 1502703982149,
      "end": 1502703982150,
      "fromCache": true,
      "ip": "216.58.212.104"
    }
  },
  {
    "type": "request",
    "details": {
      "frameId": 0,
      "method": "GET",
      "parentFrameId": -1,
      "requestId": "3892",
      "tabId": 2,
      "type": "image",
      "url": "https://ebookee.org/img/h3-bg.png",
      "id": 4043,
      "contextId": 326,
      "parentContextId": -1,
      "windowId": 1,
      "start": 1502703982155,
      "end": 1502703982155,
      "requestHeaders": [
        {
          "name": "User-Agent",
          "value": "Mozilla/5.0 (X11; Linux x86_64) AppleWebKit/537.36 (KHTML, like Gecko) Chrome/60.0.3112.90 Safari/537.36"
        },
        {
          "name": "Accept",
          "value": "image/webp,image/apng,image/*,*/*;q=0.8"
        },
        {
          "name": "Referer",
          "value": "https://ebookee.org/css/main.min.css?20170220"
        },
        {
          "name": "Accept-Encoding",
          "value": "gzip, deflate, br"
        },
        {
          "name": "Accept-Language",
          "value": "en-GB,en-US;q=0.8,en;q=0.6"
        },
        {
          "name": "Cookie",
          "value": "vs=0"
        }
      ]
    }
  },
  {
    "type": "response",
    "details": {
      "frameId": 0,
      "method": "GET",
      "parentFrameId": -1,
      "requestId": "3887",
      "responseHeaders": [
        {
          "name": "status",
          "value": "200"
        },
        {
          "name": "server",
          "value": "nginx"
        },
        {
          "name": "date",
          "value": "Mon, 14 Aug 2017 09:46:22 GMT"
        },
        {
          "name": "content-type",
          "value": "image/gif"
        },
        {
          "name": "content-length",
          "value": "4409"
        },
        {
          "name": "last-modified",
          "value": "Sun, 01 May 2016 05:07:14 GMT"
        },
        {
          "name": "etag",
          "value": "\"57258f02-1139\""
        },
        {
          "name": "expires",
          "value": "Wed, 13 Sep 2017 09:46:22 GMT"
        },
        {
          "name": "cache-control",
          "value": "max-age=2592000"
        },
        {
          "name": "accept-ranges",
          "value": "bytes"
        }
      ],
      "statusCode": 200,
      "statusLine": "HTTP/1.1 200",
      "tabId": 2,
      "type": "image",
      "url": "https://ebookee.org/img/search.gif",
      "id": 4039,
      "contextId": 326,
      "parentContextId": -1,
      "windowId": 1,
      "start": 1502703982157,
      "end": 1502703982157,
      "fromCache": false,
      "ip": "185.7.34.123"
    }
  },
  {
    "type": "response",
    "details": {
      "frameId": 0,
      "method": "GET",
      "parentFrameId": -1,
      "requestId": "3888",
      "responseHeaders": [
        {
          "name": "status",
          "value": "200"
        },
        {
          "name": "server",
          "value": "nginx"
        },
        {
          "name": "date",
          "value": "Mon, 14 Aug 2017 09:46:22 GMT"
        },
        {
          "name": "content-type",
          "value": "image/png"
        },
        {
          "name": "content-length",
          "value": "1383"
        },
        {
          "name": "last-modified",
          "value": "Sun, 01 May 2016 05:07:14 GMT"
        },
        {
          "name": "etag",
          "value": "\"57258f02-567\""
        },
        {
          "name": "expires",
          "value": "Wed, 13 Sep 2017 09:46:22 GMT"
        },
        {
          "name": "cache-control",
          "value": "max-age=2592000"
        },
        {
          "name": "accept-ranges",
          "value": "bytes"
        }
      ],
      "statusCode": 200,
      "statusLine": "HTTP/1.1 200",
      "tabId": 2,
      "type": "image",
      "url": "https://ebookee.org/img/sb.png",
      "id": 4040,
      "contextId": 326,
      "parentContextId": -1,
      "windowId": 1,
      "start": 1502703982157,
      "end": 1502703982157,
      "fromCache": false,
      "ip": "185.7.34.123"
    }
  },
  {
    "type": "response",
    "details": {
      "frameId": 0,
      "method": "GET",
      "parentFrameId": -1,
      "requestId": "3889",
      "responseHeaders": [
        {
          "name": "status",
          "value": "200"
        },
        {
          "name": "server",
          "value": "nginx"
        },
        {
          "name": "date",
          "value": "Mon, 14 Aug 2017 09:46:22 GMT"
        },
        {
          "name": "content-type",
          "value": "image/gif"
        },
        {
          "name": "content-length",
          "value": "131"
        },
        {
          "name": "last-modified",
          "value": "Sun, 01 May 2016 05:07:14 GMT"
        },
        {
          "name": "etag",
          "value": "\"57258f02-83\""
        },
        {
          "name": "expires",
          "value": "Wed, 13 Sep 2017 09:46:22 GMT"
        },
        {
          "name": "cache-control",
          "value": "max-age=2592000"
        },
        {
          "name": "accept-ranges",
          "value": "bytes"
        }
      ],
      "statusCode": 200,
      "statusLine": "HTTP/1.1 200",
      "tabId": 2,
      "type": "image",
      "url": "https://ebookee.org/img/gotop.gif",
      "id": 4041,
      "contextId": 326,
      "parentContextId": -1,
      "windowId": 1,
      "start": 1502703982157,
      "end": 1502703982159,
      "fromCache": false,
      "ip": "185.7.34.123"
    }
  },
  {
    "type": "response",
    "details": {
      "frameId": 0,
      "method": "GET",
      "parentFrameId": -1,
      "requestId": "3890",
      "responseHeaders": [
        {
          "name": "status",
          "value": "200"
        },
        {
          "name": "content-encoding",
          "value": "gzip"
        },
        {
          "name": "accept-ranges",
          "value": "bytes"
        },
        {
          "name": "cache-control",
          "value": "max-age=604800"
        },
        {
          "name": "content-type",
          "value": "application/x-javascript"
        },
        {
          "name": "date",
          "value": "Mon, 14 Aug 2017 09:46:22 GMT"
        },
        {
          "name": "expires",
          "value": "Mon, 14 Aug 2017 09:46:22 GMT"
        },
        {
          "name": "last-modified",
          "value": "Tue, 1 Aug 2017 13:20:11 GMT"
        },
        {
          "name": "server",
          "value": "ECS (lcy/1D1F)"
        },
        {
          "name": "vary",
          "value": "Accept-Encoding"
        },
        {
          "name": "x-cache",
          "value": "HIT"
        },
        {
          "name": "content-length",
          "value": "38332"
        }
      ],
      "statusCode": 200,
      "statusLine": "HTTP/1.1 200",
      "tabId": 2,
      "type": "script",
      "url": "https://i.po.st/static/v3/post-widget.js#publisherKey=https://ebookee.org-498",
      "id": 4038,
      "contextId": 326,
      "parentContextId": -1,
      "windowId": 1,
      "start": 1502703982159,
      "end": 1502703982161,
      "fromCache": false,
      "ip": "192.229.233.175"
    }
  },
  {
    "type": "response",
    "details": {
      "frameId": 0,
      "method": "GET",
      "parentFrameId": -1,
      "requestId": "3892",
      "responseHeaders": [
        {
          "name": "status",
          "value": "200"
        },
        {
          "name": "server",
          "value": "nginx"
        },
        {
          "name": "date",
          "value": "Mon, 14 Aug 2017 09:46:22 GMT"
        },
        {
          "name": "content-type",
          "value": "image/png"
        },
        {
          "name": "content-length",
          "value": "1240"
        },
        {
          "name": "last-modified",
          "value": "Sun, 01 May 2016 05:07:14 GMT"
        },
        {
          "name": "etag",
          "value": "\"57258f02-4d8\""
        },
        {
          "name": "expires",
          "value": "Wed, 13 Sep 2017 09:46:22 GMT"
        },
        {
          "name": "cache-control",
          "value": "max-age=2592000"
        },
        {
          "name": "accept-ranges",
          "value": "bytes"
        }
      ],
      "statusCode": 200,
      "statusLine": "HTTP/1.1 200",
      "tabId": 2,
      "type": "image",
      "url": "https://ebookee.org/img/h3-bg.png",
      "id": 4043,
      "contextId": 326,
      "parentContextId": -1,
      "windowId": 1,
      "start": 1502703982165,
      "end": 1502703982165,
      "fromCache": false,
      "ip": "185.7.34.123"
    }
  },
  {
    "type": "cookie.changed",
    "details": {
      "cause": "explicit",
      "cookie": {
        "domain": ".ebookee.org",
        "expirationDate": 1565775982,
        "hostOnly": false,
        "httpOnly": false,
        "name": "__utma",
        "path": "/",
        "sameSite": "no_restriction",
        "secure": false,
        "session": false,
        "storeId": "0",
        "value": "246647376.1276404275.1502703982.1502703982.1502703982.1"
      },
      "removed": false,
      "timeStamp": 1502703982190
    }
  },
  {
    "type": "variable.change",
    "details": {
      "name": "__utma",
      "type": "cookie",
      "value": "246647376.1276404275.1502703982.1502703982.1502703982.1",
      "timeStamp": 1502703982190
    }
  },
  {
    "type": "cookie.changed",
    "details": {
      "cause": "explicit",
      "cookie": {
        "domain": ".ebookee.org",
        "expirationDate": 1502705782,
        "hostOnly": false,
        "httpOnly": false,
        "name": "__utmb",
        "path": "/",
        "sameSite": "no_restriction",
        "secure": false,
        "session": false,
        "storeId": "0",
        "value": "246647376.0.10.1502703982"
      },
      "removed": false,
      "timeStamp": 1502703982190
    }
  },
  {
    "type": "variable.change",
    "details": {
      "name": "__utmb",
      "type": "cookie",
      "value": "246647376.0.10.1502703982",
      "timeStamp": 1502703982190
    }
  },
  {
    "type": "cookie.changed",
    "details": {
      "cause": "explicit",
      "cookie": {
        "domain": ".ebookee.org",
        "hostOnly": false,
        "httpOnly": false,
        "name": "__utmc",
        "path": "/",
        "sameSite": "no_restriction",
        "secure": false,
        "session": true,
        "storeId": "0",
        "value": "246647376"
      },
      "removed": false,
      "timeStamp": 1502703982190
    }
  },
  {
    "type": "variable.change",
    "details": {
      "name": "__utmc",
      "type": "cookie",
      "value": "246647376",
      "timeStamp": 1502703982190
    }
  },
  {
    "type": "cookie.changed",
    "details": {
      "cause": "explicit",
      "cookie": {
        "domain": ".ebookee.org",
        "expirationDate": 1518471982,
        "hostOnly": false,
        "httpOnly": false,
        "name": "__utmz",
        "path": "/",
        "sameSite": "no_restriction",
        "secure": false,
        "session": false,
        "storeId": "0",
        "value": "246647376.1502703982.1.1.utmcsr=(direct)|utmccn=(direct)|utmcmd=(none)"
      },
      "removed": false,
      "timeStamp": 1502703982191
    }
  },
  {
    "type": "variable.change",
    "details": {
      "name": "__utmz",
      "type": "cookie",
      "value": "246647376.1502703982.1.1.utmcsr=(direct)|utmccn=(direct)|utmcmd=(none)",
      "timeStamp": 1502703982191
    }
  },
  {
    "type": "cookie.changed",
    "details": {
      "cause": "explicit",
      "cookie": {
        "domain": ".ebookee.org",
        "expirationDate": 1502704582,
        "hostOnly": false,
        "httpOnly": false,
        "name": "__utmt",
        "path": "/",
        "sameSite": "no_restriction",
        "secure": false,
        "session": false,
        "storeId": "0",
        "value": "1"
      },
      "removed": false,
      "timeStamp": 1502703982201
    }
  },
  {
    "type": "variable.change",
    "details": {
      "name": "__utmt",
      "type": "cookie",
      "value": "1",
      "timeStamp": 1502703982201
    }
  },
  {
    "type": "cookie.changed",
    "details": {
      "cause": "overwrite",
      "cookie": {
        "domain": ".ebookee.org",
        "expirationDate": 1565775982,
        "hostOnly": false,
        "httpOnly": false,
        "name": "__utma",
        "path": "/",
        "sameSite": "no_restriction",
        "secure": false,
        "session": false,
        "storeId": "0",
        "value": "246647376.1276404275.1502703982.1502703982.1502703982.1"
      },
      "removed": true,
      "timeStamp": 1502703982201
    }
  },
  {
    "type": "variable.change",
    "details": {
      "name": "__utma",
      "type": "cookie",
      "value": "246647376.1276404275.1502703982.1502703982.1502703982.1",
      "timeStamp": 1502703982201
    }
  },
  {
    "type": "cookie.changed",
    "details": {
      "cause": "explicit",
      "cookie": {
        "domain": ".ebookee.org",
        "expirationDate": 1565775982,
        "hostOnly": false,
        "httpOnly": false,
        "name": "__utma",
        "path": "/",
        "sameSite": "no_restriction",
        "secure": false,
        "session": false,
        "storeId": "0",
        "value": "246647376.1276404275.1502703982.1502703982.1502703982.1"
      },
      "removed": false,
      "timeStamp": 1502703982201
    }
  },
  {
    "type": "variable.change",
    "details": {
      "name": "__utma",
      "type": "cookie",
      "value": "246647376.1276404275.1502703982.1502703982.1502703982.1",
      "timeStamp": 1502703982201
    }
  },
  {
    "type": "cookie.changed",
    "details": {
      "cause": "overwrite",
      "cookie": {
        "domain": ".ebookee.org",
        "expirationDate": 1502705782,
        "hostOnly": false,
        "httpOnly": false,
        "name": "__utmb",
        "path": "/",
        "sameSite": "no_restriction",
        "secure": false,
        "session": false,
        "storeId": "0",
        "value": "246647376.0.10.1502703982"
      },
      "removed": true,
      "timeStamp": 1502703982201
    }
  },
  {
    "type": "variable.change",
    "details": {
      "name": "__utmb",
      "type": "cookie",
      "value": "246647376.0.10.1502703982",
      "timeStamp": 1502703982201
    }
  },
  {
    "type": "cookie.changed",
    "details": {
      "cause": "explicit",
      "cookie": {
        "domain": ".ebookee.org",
        "expirationDate": 1502705782,
        "hostOnly": false,
        "httpOnly": false,
        "name": "__utmb",
        "path": "/",
        "sameSite": "no_restriction",
        "secure": false,
        "session": false,
        "storeId": "0",
        "value": "246647376.1.10.1502703982"
      },
      "removed": false,
      "timeStamp": 1502703982201
    }
  },
  {
    "type": "variable.change",
    "details": {
      "name": "__utmb",
      "type": "cookie",
      "value": "246647376.1.10.1502703982",
      "timeStamp": 1502703982201
    }
  },
  {
    "type": "cookie.changed",
    "details": {
      "cause": "overwrite",
      "cookie": {
        "domain": ".ebookee.org",
        "hostOnly": false,
        "httpOnly": false,
        "name": "__utmc",
        "path": "/",
        "sameSite": "no_restriction",
        "secure": false,
        "session": true,
        "storeId": "0",
        "value": "246647376"
      },
      "removed": true,
      "timeStamp": 1502703982201
    }
  },
  {
    "type": "variable.change",
    "details": {
      "name": "__utmc",
      "type": "cookie",
      "value": "246647376",
      "timeStamp": 1502703982201
    }
  },
  {
    "type": "cookie.changed",
    "details": {
      "cause": "explicit",
      "cookie": {
        "domain": ".ebookee.org",
        "hostOnly": false,
        "httpOnly": false,
        "name": "__utmc",
        "path": "/",
        "sameSite": "no_restriction",
        "secure": false,
        "session": true,
        "storeId": "0",
        "value": "246647376"
      },
      "removed": false,
      "timeStamp": 1502703982201
    }
  },
  {
    "type": "variable.change",
    "details": {
      "name": "__utmc",
      "type": "cookie",
      "value": "246647376",
      "timeStamp": 1502703982201
    }
  },
  {
    "type": "cookie.changed",
    "details": {
      "cause": "overwrite",
      "cookie": {
        "domain": ".ebookee.org",
        "expirationDate": 1518471982,
        "hostOnly": false,
        "httpOnly": false,
        "name": "__utmz",
        "path": "/",
        "sameSite": "no_restriction",
        "secure": false,
        "session": false,
        "storeId": "0",
        "value": "246647376.1502703982.1.1.utmcsr=(direct)|utmccn=(direct)|utmcmd=(none)"
      },
      "removed": true,
      "timeStamp": 1502703982201
    }
  },
  {
    "type": "variable.change",
    "details": {
      "name": "__utmz",
      "type": "cookie",
      "value": "246647376.1502703982.1.1.utmcsr=(direct)|utmccn=(direct)|utmcmd=(none)",
      "timeStamp": 1502703982201
    }
  },
  {
    "type": "cookie.changed",
    "details": {
      "cause": "explicit",
      "cookie": {
        "domain": ".ebookee.org",
        "expirationDate": 1518471982,
        "hostOnly": false,
        "httpOnly": false,
        "name": "__utmz",
        "path": "/",
        "sameSite": "no_restriction",
        "secure": false,
        "session": false,
        "storeId": "0",
        "value": "246647376.1502703982.1.1.utmcsr=(direct)|utmccn=(direct)|utmcmd=(none)"
      },
      "removed": false,
      "timeStamp": 1502703982201
    }
  },
  {
    "type": "variable.change",
    "details": {
      "name": "__utmz",
      "type": "cookie",
      "value": "246647376.1502703982.1.1.utmcsr=(direct)|utmccn=(direct)|utmcmd=(none)",
      "timeStamp": 1502703982201
    }
  },
  {
    "type": "request",
    "details": {
      "frameId": 0,
      "method": "GET",
      "parentFrameId": -1,
      "requestId": "3893",
      "tabId": 2,
      "type": "image",
      "url": "https://ssl.google-analytics.com/r/__utm.gif?utmwv=5.6.7&utms=1&utmn=721597710&utmhn=ebookee.org&utmcs=UTF-8&utmsr=1920x1080&utmvp=920x823&utmsc=24-bit&utmul=en-gb&utmje=0&utmfl=24.0%20r0&utmdt=Ebookee%3A%20Free%20Download%20eBooks%20Search%20Engine!&utmhid=1828428069&utmr=-&utmp=%2F&utmht=1502703982192&utmac=UA-1973059-1&utmcc=__utma%3D246647376.1276404275.1502703982.1502703982.1502703982.1%3B%2B__utmz%3D246647376.1502703982.1.1.utmcsr%3D(direct)%7Cutmccn%3D(direct)%7Cutmcmd%3D(none)%3B&utmjid=243623614&utmredir=1&utmu=qhAAAAAAAAAAAAAAAAAAAAAE~",
      "id": 4044,
      "contextId": 326,
      "parentContextId": -1,
      "windowId": 1,
      "start": 1502703982201,
      "end": 1502703982201,
      "requestHeaders": [
        {
          "name": "User-Agent",
          "value": "Mozilla/5.0 (X11; Linux x86_64) AppleWebKit/537.36 (KHTML, like Gecko) Chrome/60.0.3112.90 Safari/537.36"
        },
        {
          "name": "Accept",
          "value": "image/webp,image/apng,image/*,*/*;q=0.8"
        },
        {
          "name": "Referer",
          "value": "https://ebookee.org/"
        },
        {
          "name": "Accept-Encoding",
          "value": "gzip, deflate, br"
        },
        {
          "name": "Accept-Language",
          "value": "en-GB,en-US;q=0.8,en;q=0.6"
        }
      ]
    }
  },
  {
    "type": "response",
    "details": {
      "frameId": 0,
      "method": "GET",
      "parentFrameId": -1,
      "requestId": "3893",
      "responseHeaders": [
        {
          "name": "status",
          "value": "200"
        },
        {
          "name": "access-control-allow-origin",
          "value": "*"
        },
        {
          "name": "date",
          "value": "Mon, 14 Aug 2017 09:46:22 GMT"
        },
        {
          "name": "pragma",
          "value": "no-cache"
        },
        {
          "name": "expires",
          "value": "Fri, 01 Jan 1990 00:00:00 GMT"
        },
        {
          "name": "cache-control",
          "value": "no-cache, no-store, must-revalidate"
        },
        {
          "name": "last-modified",
          "value": "Sun, 17 May 1998 03:00:00 GMT"
        },
        {
          "name": "x-content-type-options",
          "value": "nosniff"
        },
        {
          "name": "content-type",
          "value": "image/gif"
        },
        {
          "name": "server",
          "value": "Golfe2"
        },
        {
          "name": "content-length",
          "value": "35"
        },
        {
          "name": "alt-svc",
          "value": "quic=\":443\"; ma=2592000; v=\"39,38,37,35\""
        }
      ],
      "statusCode": 200,
      "statusLine": "HTTP/1.1 200",
      "tabId": 2,
      "type": "image",
      "url": "https://ssl.google-analytics.com/r/__utm.gif?utmwv=5.6.7&utms=1&utmn=721597710&utmhn=ebookee.org&utmcs=UTF-8&utmsr=1920x1080&utmvp=920x823&utmsc=24-bit&utmul=en-gb&utmje=0&utmfl=24.0%20r0&utmdt=Ebookee%3A%20Free%20Download%20eBooks%20Search%20Engine!&utmhid=1828428069&utmr=-&utmp=%2F&utmht=1502703982192&utmac=UA-1973059-1&utmcc=__utma%3D246647376.1276404275.1502703982.1502703982.1502703982.1%3B%2B__utmz%3D246647376.1502703982.1.1.utmcsr%3D(direct)%7Cutmccn%3D(direct)%7Cutmcmd%3D(none)%3B&utmjid=243623614&utmredir=1&utmu=qhAAAAAAAAAAAAAAAAAAAAAE~",
      "id": 4044,
      "contextId": 326,
      "parentContextId": -1,
      "windowId": 1,
      "start": 1502703982211,
      "end": 1502703982211,
      "fromCache": false,
      "ip": "216.58.206.72"
    }
  },
  {
    "type": "request",
    "details": {
      "frameId": 0,
      "method": "GET",
      "parentFrameId": -1,
      "requestId": "3894",
      "tabId": 2,
      "type": "stylesheet",
      "url": "https://s.po.st/static/v3/css/r1post.css?4_32_2_pch_1126",
      "id": 4045,
      "contextId": 326,
      "parentContextId": -1,
      "windowId": 1,
      "start": 1502703982224,
      "end": 1502703982224,
      "requestHeaders": [
        {
          "name": "User-Agent",
          "value": "Mozilla/5.0 (X11; Linux x86_64) AppleWebKit/537.36 (KHTML, like Gecko) Chrome/60.0.3112.90 Safari/537.36"
        },
        {
          "name": "Accept",
          "value": "text/css,*/*;q=0.1"
        },
        {
          "name": "Referer",
          "value": "https://ebookee.org/"
        },
        {
          "name": "Accept-Encoding",
          "value": "gzip, deflate, br"
        },
        {
          "name": "Accept-Language",
          "value": "en-GB,en-US;q=0.8,en;q=0.6"
        },
        {
          "name": "Cookie",
          "value": "post_dcm=17392; post_uuid=27919174-8174-4091-a6a8-95b9da1c898f"
        }
      ]
    }
  },
  {
    "type": "navigation.dOMContentLoaded",
    "details": {
      "frameId": 0,
      "processId": 47,
      "tabId": 2,
      "timeStamp": 1502703982224,
      "url": "https://ebookee.org/",
      "windowId": 1
    }
  },
  {
    "type": "response",
    "details": {
      "frameId": 0,
      "method": "GET",
      "parentFrameId": -1,
      "requestId": "3894",
      "responseHeaders": [
        {
          "name": "status",
          "value": "200"
        },
        {
          "name": "content-encoding",
          "value": "gzip"
        },
        {
          "name": "accept-ranges",
          "value": "bytes"
        },
        {
          "name": "cache-control",
          "value": "public, max-age=31449600"
        },
        {
          "name": "content-type",
          "value": "text/css"
        },
        {
          "name": "date",
          "value": "Mon, 14 Aug 2017 09:41:19 GMT"
        },
        {
          "name": "expires",
          "value": "Thu, 26 Jul 2018 08:52:17 GMT"
        },
        {
          "name": "last-modified",
          "value": "Wed, 26 Jul 2017 08:32:43 GMT"
        },
        {
          "name": "server",
          "value": "ECS (lcy/1D0F)"
        },
        {
          "name": "vary",
          "value": "Accept-Encoding"
        },
        {
          "name": "x-cache",
          "value": "HIT"
        },
        {
          "name": "content-length",
          "value": "9952"
        }
      ],
      "statusCode": 200,
      "statusLine": "HTTP/1.1 200",
      "tabId": 2,
      "type": "stylesheet",
      "url": "https://s.po.st/static/v3/css/r1post.css?4_32_2_pch_1126",
      "id": 4045,
      "contextId": 326,
      "parentContextId": -1,
      "windowId": 1,
      "start": 1502703982224,
      "end": 1502703982225,
      "fromCache": true,
      "ip": "192.229.233.175"
    }
  },
  {
    "type": "request",
    "details": {
      "frameId": 0,
      "method": "GET",
      "parentFrameId": -1,
      "requestId": "3895",
      "tabId": 2,
      "type": "script",
      "url": "https://po.st/v1/status?pubKey=https%3A%2F%2Febookee.org-498&1502703982240&callback=r1PoStJSONP3275",
      "id": 4046,
      "contextId": 326,
      "parentContextId": -1,
      "windowId": 1,
      "start": 1502703982240,
      "end": 1502703982240,
      "requestHeaders": [
        {
          "name": "User-Agent",
          "value": "Mozilla/5.0 (X11; Linux x86_64) AppleWebKit/537.36 (KHTML, like Gecko) Chrome/60.0.3112.90 Safari/537.36"
        },
        {
          "name": "Accept",
          "value": "*/*"
        },
        {
          "name": "Referer",
          "value": "https://ebookee.org/"
        },
        {
          "name": "Accept-Encoding",
          "value": "gzip, deflate, br"
        },
        {
          "name": "Accept-Language",
          "value": "en-GB,en-US;q=0.8,en;q=0.6"
        },
        {
          "name": "Cookie",
          "value": "post_dcm=17392; post_uuid=27919174-8174-4091-a6a8-95b9da1c898f"
        }
      ]
    }
  },
  {
    "type": "request",
    "details": {
      "frameId": 0,
      "method": "GET",
      "parentFrameId": -1,
      "requestId": "3896",
      "tabId": 2,
      "type": "image",
      "url": "https://s.po.st/static/v3/img/set-32.png?27052015",
      "id": 4047,
      "contextId": 326,
      "parentContextId": -1,
      "windowId": 1,
      "start": 1502703982243,
      "end": 1502703982243,
      "requestHeaders": [
        {
          "name": "User-Agent",
          "value": "Mozilla/5.0 (X11; Linux x86_64) AppleWebKit/537.36 (KHTML, like Gecko) Chrome/60.0.3112.90 Safari/537.36"
        },
        {
          "name": "Accept",
          "value": "image/webp,image/apng,image/*,*/*;q=0.8"
        },
        {
          "name": "Referer",
          "value": "https://s.po.st/static/v3/css/r1post.css?4_32_2_pch_1126"
        },
        {
          "name": "Accept-Encoding",
          "value": "gzip, deflate, br"
        },
        {
          "name": "Accept-Language",
          "value": "en-GB,en-US;q=0.8,en;q=0.6"
        },
        {
          "name": "Cookie",
          "value": "post_dcm=17392; post_uuid=27919174-8174-4091-a6a8-95b9da1c898f"
        }
      ]
    }
  },
  {
    "type": "response",
    "details": {
      "frameId": 0,
      "method": "GET",
      "parentFrameId": -1,
      "requestId": "3896",
      "responseHeaders": [
        {
          "name": "status",
          "value": "200"
        },
        {
          "name": "accept-ranges",
          "value": "bytes"
        },
        {
          "name": "cache-control",
          "value": "max-age=604800"
        },
        {
          "name": "content-type",
          "value": "image/png"
        },
        {
          "name": "date",
          "value": "Mon, 14 Aug 2017 09:46:22 GMT"
        },
        {
          "name": "expires",
          "value": "Thu, 10 Aug 2017 08:52:20 GMT"
        },
        {
          "name": "last-modified",
          "value": "Tue, 1 Aug 2017 13:20:11 GMT"
        },
        {
          "name": "server",
          "value": "ECS (lcy/1D52)"
        },
        {
          "name": "x-cache",
          "value": "HIT"
        },
        {
          "name": "content-length",
          "value": "41178"
        }
      ],
      "statusCode": 200,
      "statusLine": "HTTP/1.1 200",
      "tabId": 2,
      "type": "image",
      "url": "https://s.po.st/static/v3/img/set-32.png?27052015",
      "id": 4047,
      "contextId": 326,
      "parentContextId": -1,
      "windowId": 1,
      "start": 1502703982247,
      "end": 1502703982249,
      "fromCache": false,
      "ip": "192.229.233.175"
    }
  },
  {
    "type": "variable.new",
    "details": {
      "name": "",
      "type": "location",
      "value": "https://ebookee.org/",
      "timeStamp": 1502703982251,
      "tabId": 2,
      "frameId": 0,
      "url": "https://ebookee.org/",
      "contextId": 326,
      "windowId": 1
    }
  },
  {
    "type": "variable.new",
    "details": {
      "name": "",
      "type": "user-agent",
      "value": "Mozilla/5.0 (X11; Linux x86_64) AppleWebKit/537.36 (KHTML, like Gecko) Chrome/60.0.3112.90 Safari/537.36",
      "timeStamp": 1502703982251,
      "tabId": 2,
      "frameId": 0,
      "url": "https://ebookee.org/",
      "contextId": 326,
      "windowId": 1
    }
  },
  {
    "type": "variable.new",
    "details": {
      "name": "",
      "type": "title",
      "value": "Ebookee: Free Download eBooks Search Engine!",
      "timeStamp": 1502703982251,
      "tabId": 2,
      "frameId": 0,
      "url": "https://ebookee.org/",
      "contextId": 326,
      "windowId": 1
    }
  },
  {
    "type": "variable.new",
    "details": {
      "name": "q",
      "type": "input:text",
      "value": "",
      "timeStamp": 1502703982251,
      "tabId": 2,
      "frameId": 0,
      "url": "https://ebookee.org/",
      "contextId": 326,
      "windowId": 1
    }
  },
  {
    "type": "variable.change",
    "details": {
      "name": "q",
      "type": "input:text",
      "value": "",
      "timeStamp": 1502703982251,
      "tabId": 2,
      "frameId": 0,
      "url": "https://ebookee.org/",
      "contextId": 326,
      "windowId": 1
    }
  },
  {
    "type": "variable.new",
    "details": {
      "name": "sa",
      "type": "input:submit",
      "value": "",
      "timeStamp": 1502703982251,
      "tabId": 2,
      "frameId": 0,
      "url": "https://ebookee.org/",
      "contextId": 326,
      "windowId": 1
    }
  },
  {
    "type": "variable.new",
    "details": {
      "name": "email",
      "type": "input:text",
      "value": "",
      "timeStamp": 1502703982251,
      "tabId": 2,
      "frameId": 0,
      "url": "https://ebookee.org/",
      "contextId": 326,
      "windowId": 1
    }
  },
  {
    "type": "variable.new",
    "details": {
      "name": "url",
      "type": "input:hidden",
      "value": "",
      "timeStamp": 1502703982251,
      "tabId": 2,
      "frameId": 0,
      "url": "https://ebookee.org/",
      "contextId": 326,
      "windowId": 1
    }
  },
  {
    "type": "variable.new",
    "details": {
      "name": "title",
      "type": "input:hidden",
      "value": "",
      "timeStamp": 1502703982251,
      "tabId": 2,
      "frameId": 0,
      "url": "https://ebookee.org/",
      "contextId": 326,
      "windowId": 1
    }
  },
  {
    "type": "variable.new",
    "details": {
      "name": "loc",
      "type": "input:hidden",
      "value": "",
      "timeStamp": 1502703982252,
      "tabId": 2,
      "frameId": 0,
      "url": "https://ebookee.org/",
      "contextId": 326,
      "windowId": 1
    }
  },
  {
    "type": "variable.new",
    "details": {
      "name": null,
      "type": "input:submit",
      "value": "",
      "timeStamp": 1502703982252,
      "tabId": 2,
      "frameId": 0,
      "url": "https://ebookee.org/",
      "contextId": 326,
      "windowId": 1
    }
  },
  {
    "type": "dom.resize",
    "details": {
      "isTrusted": true,
      "type": "resize",
      "target": "#window",
      "currentTarget": "#window",
      "eventPhase": 2,
      "bubbles": false,
      "cancelable": false,
      "defaultPrevented": false,
      "composed": false,
      "timeStamp": 1502703982288,
      "srcElement": "#window",
      "returnValue": true,
      "cancelBubble": false,
      "path": "#window",
      "tabId": 2,
      "frameId": 0,
      "url": "https://ebookee.org/",
      "contextId": 326,
      "windowId": 1
    }
  },
  {
    "type": "dom.resize",
    "details": {
      "isTrusted": true,
      "type": "resize",
      "target": "#window",
      "currentTarget": "#window",
      "eventPhase": 2,
      "bubbles": false,
      "cancelable": false,
      "defaultPrevented": false,
      "composed": false,
      "timeStamp": 1502703982302,
      "srcElement": "#window",
      "returnValue": true,
      "cancelBubble": false,
      "path": "#window",
      "tabId": 2,
      "frameId": 0,
      "url": "https://ebookee.org/",
      "contextId": 326,
      "windowId": 1
    }
  },
  {
    "type": "request",
    "details": {
      "frameId": 0,
      "method": "GET",
      "parentFrameId": -1,
      "requestId": "3897",
      "tabId": 2,
      "type": "script",
      "url": "https://s.po.st/static/v3/js/external/copyPaste.js",
      "id": 4048,
      "contextId": 326,
      "parentContextId": -1,
      "windowId": 1,
      "start": 1502703982424,
      "end": 1502703982425,
      "requestHeaders": [
        {
          "name": "User-Agent",
          "value": "Mozilla/5.0 (X11; Linux x86_64) AppleWebKit/537.36 (KHTML, like Gecko) Chrome/60.0.3112.90 Safari/537.36"
        },
        {
          "name": "Accept",
          "value": "*/*"
        },
        {
          "name": "Referer",
          "value": "https://ebookee.org/"
        },
        {
          "name": "Accept-Encoding",
          "value": "gzip, deflate, br"
        },
        {
          "name": "Accept-Language",
          "value": "en-GB,en-US;q=0.8,en;q=0.6"
        },
        {
          "name": "Cookie",
          "value": "post_dcm=17392; post_uuid=27919174-8174-4091-a6a8-95b9da1c898f"
        }
      ]
    }
  },
  {
    "type": "request",
    "details": {
      "frameId": 0,
      "method": "GET",
      "parentFrameId": -1,
      "requestId": "3898",
      "tabId": 2,
      "type": "script",
      "url": "https://sb.scorecardresearch.com/beacon.js",
      "id": 4049,
      "contextId": 326,
      "parentContextId": -1,
      "windowId": 1,
      "start": 1502703982425,
      "end": 1502703982425,
      "requestHeaders": [
        {
          "name": "User-Agent",
          "value": "Mozilla/5.0 (X11; Linux x86_64) AppleWebKit/537.36 (KHTML, like Gecko) Chrome/60.0.3112.90 Safari/537.36"
        },
        {
          "name": "Accept",
          "value": "*/*"
        },
        {
          "name": "Referer",
          "value": "https://ebookee.org/"
        },
        {
          "name": "Accept-Encoding",
          "value": "gzip, deflate, br"
        },
        {
          "name": "Accept-Language",
          "value": "en-GB,en-US;q=0.8,en;q=0.6"
        },
        {
          "name": "Cookie",
          "value": "UID=1B888a22151a93a58d872011502703571; UIDR=1502703571"
        }
      ]
    }
  },
  {
    "type": "response",
    "details": {
      "frameId": 0,
      "method": "GET",
      "parentFrameId": -1,
      "requestId": "3897",
      "responseHeaders": [
        {
          "name": "status",
          "value": "200"
        },
        {
          "name": "content-encoding",
          "value": "gzip"
        },
        {
          "name": "accept-ranges",
          "value": "bytes"
        },
        {
          "name": "cache-control",
          "value": "max-age=604800"
        },
        {
          "name": "content-type",
          "value": "application/x-javascript"
        },
        {
          "name": "date",
          "value": "Mon, 14 Aug 2017 09:41:19 GMT"
        },
        {
          "name": "expires",
          "value": "Mon, 14 Aug 2017 09:41:19 GMT"
        },
        {
          "name": "last-modified",
          "value": "Tue, 1 Aug 2017 13:20:11 GMT"
        },
        {
          "name": "server",
          "value": "ECS (lcy/1D2D)"
        },
        {
          "name": "vary",
          "value": "Accept-Encoding"
        },
        {
          "name": "x-cache",
          "value": "HIT"
        },
        {
          "name": "content-length",
          "value": "1501"
        }
      ],
      "statusCode": 200,
      "statusLine": "HTTP/1.1 200",
      "tabId": 2,
      "type": "script",
      "url": "https://s.po.st/static/v3/js/external/copyPaste.js",
      "id": 4048,
      "contextId": 326,
      "parentContextId": -1,
      "windowId": 1,
      "start": 1502703982426,
      "end": 1502703982427,
      "fromCache": true,
      "ip": "192.229.233.175"
    }
  },
  {
    "type": "response",
    "details": {
      "frameId": 0,
      "method": "GET",
      "parentFrameId": -1,
      "requestId": "3898",
      "responseHeaders": [
        {
          "name": "Content-Type",
          "value": "application/x-javascript"
        },
        {
          "name": "Vary",
          "value": "Accept-Encoding"
        },
        {
          "name": "Content-Encoding",
          "value": "gzip"
        },
        {
          "name": "Expires",
          "value": "Mon, 28 Aug 2017 09:39:31 GMT"
        },
        {
          "name": "Date",
          "value": "Mon, 14 Aug 2017 09:39:31 GMT"
        },
        {
          "name": "Content-Length",
          "value": "901"
        },
        {
          "name": "Cache-Control",
          "value": "private, no-transform, max-age=1209600"
        }
      ],
      "statusCode": 200,
      "statusLine": "HTTP/1.1 200 OK",
      "tabId": 2,
      "type": "script",
      "url": "https://sb.scorecardresearch.com/beacon.js",
      "id": 4049,
      "contextId": 326,
      "parentContextId": -1,
      "windowId": 1,
      "start": 1502703982426,
      "end": 1502703982427,
      "fromCache": true,
      "ip": "104.82.70.180"
    }
  },
  {
    "type": "request",
    "details": {
      "frameId": 0,
      "method": "GET",
      "parentFrameId": -1,
      "requestId": "3899",
      "tabId": 2,
      "type": "script",
      "url": "https://s.po.st/static/v3/js/external/shareQuote.js",
      "id": 4050,
      "contextId": 326,
      "parentContextId": -1,
      "windowId": 1,
      "start": 1502703982430,
      "end": 1502703982430,
      "requestHeaders": [
        {
          "name": "User-Agent",
          "value": "Mozilla/5.0 (X11; Linux x86_64) AppleWebKit/537.36 (KHTML, like Gecko) Chrome/60.0.3112.90 Safari/537.36"
        },
        {
          "name": "Accept",
          "value": "*/*"
        },
        {
          "name": "Referer",
          "value": "https://ebookee.org/"
        },
        {
          "name": "Accept-Encoding",
          "value": "gzip, deflate, br"
        },
        {
          "name": "Accept-Language",
          "value": "en-GB,en-US;q=0.8,en;q=0.6"
        },
        {
          "name": "Cookie",
          "value": "post_dcm=17392; post_uuid=27919174-8174-4091-a6a8-95b9da1c898f"
        }
      ]
    }
  },
  {
    "type": "response",
    "details": {
      "frameId": 0,
      "method": "GET",
      "parentFrameId": -1,
      "requestId": "3899",
      "responseHeaders": [
        {
          "name": "status",
          "value": "200"
        },
        {
          "name": "content-encoding",
          "value": "gzip"
        },
        {
          "name": "accept-ranges",
          "value": "bytes"
        },
        {
          "name": "cache-control",
          "value": "max-age=43200"
        },
        {
          "name": "content-type",
          "value": "application/x-javascript"
        },
        {
          "name": "date",
          "value": "Mon, 14 Aug 2017 09:41:19 GMT"
        },
        {
          "name": "expires",
          "value": "Mon, 14 Aug 2017 09:41:19 GMT"
        },
        {
          "name": "last-modified",
          "value": "Tue, 1 Aug 2017 13:20:11 GMT"
        },
        {
          "name": "server",
          "value": "ECS (lcy/1D27)"
        },
        {
          "name": "vary",
          "value": "Accept-Encoding"
        },
        {
          "name": "x-cache",
          "value": "HIT"
        },
        {
          "name": "content-length",
          "value": "1749"
        }
      ],
      "statusCode": 200,
      "statusLine": "HTTP/1.1 200",
      "tabId": 2,
      "type": "script",
      "url": "https://s.po.st/static/v3/js/external/shareQuote.js",
      "id": 4050,
      "contextId": 326,
      "parentContextId": -1,
      "windowId": 1,
      "start": 1502703982431,
      "end": 1502703982431,
      "fromCache": true,
      "ip": "192.229.233.175"
    }
  },
  {
    "type": "request",
    "details": {
      "frameId": 0,
      "method": "GET",
      "parentFrameId": -1,
      "requestId": "3900",
      "tabId": 2,
      "type": "image",
      "url": "https://sb.scorecardresearch.com/b?c1=7&c2=8973917&c3=1&ns__t=1502703982431&ns_c=UTF-8&cv=3.1&c8=Ebookee%3A%20Free%20Download%20eBooks%20Search%20Engine!&c7=https%3A%2F%2Febookee.org%2F&c9=",
      "id": 4051,
      "contextId": 326,
      "parentContextId": -1,
      "windowId": 1,
      "start": 1502703982432,
      "end": 1502703982432,
      "requestHeaders": [
        {
          "name": "User-Agent",
          "value": "Mozilla/5.0 (X11; Linux x86_64) AppleWebKit/537.36 (KHTML, like Gecko) Chrome/60.0.3112.90 Safari/537.36"
        },
        {
          "name": "Accept",
          "value": "image/webp,image/apng,image/*,*/*;q=0.8"
        },
        {
          "name": "Referer",
          "value": "https://ebookee.org/"
        },
        {
          "name": "Accept-Encoding",
          "value": "gzip, deflate, br"
        },
        {
          "name": "Accept-Language",
          "value": "en-GB,en-US;q=0.8,en;q=0.6"
        },
        {
          "name": "Cookie",
          "value": "UID=1B888a22151a93a58d872011502703571; UIDR=1502703571"
        }
      ]
    }
  },
  {
    "type": "request",
    "details": {
      "frameId": 0,
      "method": "GET",
      "parentFrameId": -1,
      "requestId": "3901",
      "tabId": 2,
      "type": "stylesheet",
      "url": "https://s.po.st/static/v3/css/share2quote.css",
      "id": 4052,
      "contextId": 326,
      "parentContextId": -1,
      "windowId": 1,
      "start": 1502703982435,
      "end": 1502703982435,
      "requestHeaders": [
        {
          "name": "User-Agent",
          "value": "Mozilla/5.0 (X11; Linux x86_64) AppleWebKit/537.36 (KHTML, like Gecko) Chrome/60.0.3112.90 Safari/537.36"
        },
        {
          "name": "Accept",
          "value": "text/css,*/*;q=0.1"
        },
        {
          "name": "Referer",
          "value": "https://ebookee.org/"
        },
        {
          "name": "Accept-Encoding",
          "value": "gzip, deflate, br"
        },
        {
          "name": "Accept-Language",
          "value": "en-GB,en-US;q=0.8,en;q=0.6"
        },
        {
          "name": "Cookie",
          "value": "post_dcm=17392; post_uuid=27919174-8174-4091-a6a8-95b9da1c898f"
        }
      ]
    }
  },
  {
    "type": "response",
    "details": {
      "frameId": 0,
      "method": "GET",
      "parentFrameId": -1,
      "requestId": "3901",
      "responseHeaders": [
        {
          "name": "status",
          "value": "200"
        },
        {
          "name": "content-encoding",
          "value": "gzip"
        },
        {
          "name": "accept-ranges",
          "value": "bytes"
        },
        {
          "name": "cache-control",
          "value": "max-age=604800"
        },
        {
          "name": "content-type",
          "value": "text/css"
        },
        {
          "name": "date",
          "value": "Mon, 14 Aug 2017 09:41:19 GMT"
        },
        {
          "name": "expires",
          "value": "Mon, 14 Aug 2017 09:41:20 GMT"
        },
        {
          "name": "last-modified",
          "value": "Tue, 1 Aug 2017 13:20:11 GMT"
        },
        {
          "name": "server",
          "value": "ECS (lcy/1D49)"
        },
        {
          "name": "vary",
          "value": "Accept-Encoding"
        },
        {
          "name": "x-cache",
          "value": "HIT"
        },
        {
          "name": "content-length",
          "value": "636"
        }
      ],
      "statusCode": 200,
      "statusLine": "HTTP/1.1 200",
      "tabId": 2,
      "type": "stylesheet",
      "url": "https://s.po.st/static/v3/css/share2quote.css",
      "id": 4052,
      "contextId": 326,
      "parentContextId": -1,
      "windowId": 1,
      "start": 1502703982435,
      "end": 1502703982436,
      "fromCache": true,
      "ip": "192.229.233.175"
    }
  },
  {
    "type": "response",
    "details": {
      "frameId": 0,
      "method": "GET",
      "parentFrameId": -1,
      "requestId": "3900",
      "responseHeaders": [
        {
          "name": "Content-Length",
          "value": "0"
        },
        {
          "name": "Date",
          "value": "Mon, 14 Aug 2017 09:46:22 GMT"
        },
        {
          "name": "Connection",
          "value": "keep-alive"
        },
        {
          "name": "Pragma",
          "value": "no-cache"
        },
        {
          "name": "Expires",
          "value": "Mon, 01 Jan 1990 00:00:00 GMT"
        },
        {
          "name": "Cache-Control",
          "value": "private, no-cache, no-cache=Set-Cookie, no-store, proxy-revalidate"
        }
      ],
      "statusCode": 204,
      "statusLine": "HTTP/1.1 204 No Content",
      "tabId": 2,
      "type": "image",
      "url": "https://sb.scorecardresearch.com/b?c1=7&c2=8973917&c3=1&ns__t=1502703982431&ns_c=UTF-8&cv=3.1&c8=Ebookee%3A%20Free%20Download%20eBooks%20Search%20Engine!&c7=https%3A%2F%2Febookee.org%2F&c9=",
      "id": 4051,
      "contextId": 326,
      "parentContextId": -1,
      "windowId": 1,
      "start": 1502703982445,
      "end": 1502703982445,
      "fromCache": false,
      "ip": "104.82.70.180"
    }
  },
  {
    "type": "cookie.changed",
    "details": {
      "cause": "set_cookie",
      "cookie": {
        "domain": "po.st",
        "expirationDate": 1534239982,
        "hostOnly": false,
        "httpOnly": false,
        "name": "post_uuid",
        "path": "/",
        "sameSite": "no_restriction",
        "secure": false,
        "session": false,
        "storeId": -1,
        "value": "27919174-8174-4091-a6a8-95b9da1c898f"
      },
      "removed": false,
      "timeStamp": 1502703982506,
      "tabId": 2,
      "windowId": 1,
      "frameId": 0,
      "contextId": 326
    }
  },
  {
    "type": "variable.new",
    "details": {
      "name": "post_uuid",
      "type": "cookie",
      "value": "27919174-8174-4091-a6a8-95b9da1c898f",
      "timeStamp": 1502703982506,
      "tabId": 2,
      "windowId": 1,
      "frameId": 0,
      "contextId": 326
    }
  },
  {
    "type": "response",
    "details": {
      "frameId": 0,
      "method": "GET",
      "parentFrameId": -1,
      "requestId": "3895",
      "responseHeaders": [
        {
          "name": "Content-Length",
          "value": "19"
        },
        {
          "name": "Server",
          "value": "post/2.0"
        },
        {
          "name": "Pragma",
          "value": "no-cache"
        },
        {
          "name": "P3p",
          "value": "CP=\"PSAo PSDo OUR BUS DSP NON COR\""
        },
        {
          "name": "Date",
          "value": "Mon, 14 Aug 2017 09:46:22 GMT"
        },
        {
          "name": "Content-type",
          "value": "application/javascript;charset=UTF-8"
        },
        {
          "name": "Expires",
          "value": "Tue, 29 Oct 2002 19:50:44 GMT"
        },
        {
          "name": "Cache-control",
          "value": "private, no-cache, no-cache=Set-Cookie, proxy-revalidate"
        },
        {
          "name": "Set-cookie",
          "value": "post_uuid=27919174-8174-4091-a6a8-95b9da1c898f; Expires=Tue, 14-Aug-2018 09:46:22 GMT; Path=/; Domain=po.st; Version=1"
        },
        {
          "name": "Connection",
          "value": "close"
        }
      ],
      "statusCode": 200,
      "statusLine": "HTTP/1.1 200 OK",
      "tabId": 2,
      "type": "script",
      "url": "https://po.st/v1/status?pubKey=https%3A%2F%2Febookee.org-498&1502703982240&callback=r1PoStJSONP3275",
      "id": 4046,
      "contextId": 326,
      "parentContextId": -1,
      "windowId": 1,
      "start": 1502703982506,
      "end": 1502703982509,
      "fromCache": false,
      "ip": "74.217.253.90"
    }
  },
  {
    "type": "cookie.changed",
    "details": {
      "cause": "overwrite",
      "cookie": {
        "domain": ".po.st",
        "expirationDate": 1534239680,
        "hostOnly": false,
        "httpOnly": false,
        "name": "post_uuid",
        "path": "/",
        "sameSite": "no_restriction",
        "secure": false,
        "session": false,
        "storeId": "0",
        "value": "27919174-8174-4091-a6a8-95b9da1c898f"
      },
      "removed": true,
      "timeStamp": 1502703982509
    }
  },
  {
    "type": "variable.change",
    "details": {
      "name": "post_uuid",
      "type": "cookie",
      "value": "27919174-8174-4091-a6a8-95b9da1c898f",
      "timeStamp": 1502703982509
    }
  },
  {
    "type": "cookie.changed",
    "details": {
      "cause": "explicit",
      "cookie": {
        "domain": ".po.st",
        "expirationDate": 1534239982.50638,
        "hostOnly": false,
        "httpOnly": false,
        "name": "post_uuid",
        "path": "/",
        "sameSite": "no_restriction",
        "secure": false,
        "session": false,
        "storeId": "0",
        "value": "27919174-8174-4091-a6a8-95b9da1c898f"
      },
      "removed": false,
      "timeStamp": 1502703982510
    }
  },
  {
    "type": "variable.change",
    "details": {
      "name": "post_uuid",
      "type": "cookie",
      "value": "27919174-8174-4091-a6a8-95b9da1c898f",
      "timeStamp": 1502703982510
    }
  },
  {
    "type": "request",
    "details": {
      "frameId": 0,
      "method": "GET",
      "parentFrameId": -1,
      "requestId": "3902",
      "tabId": 2,
      "type": "image",
      "url": "https://p.po.st/p?t=view&pub=https%3A%2F%2Febookee.org-498&pu=https%3A%2F%2Febookee.org%2F&pt=Ebookee%3A%20Free%20Download%20eBooks%20Search%20Engine!&ru=&vw=3&v=4.32.2-pch-1126&bs=30.sl%2C01.sl%2C02.sl%2C03.sl%2C999.sl&wv=2.1&gc=%7B%22tab%22%3A%22u%22%2C%22cp%22%3A%22u%22%2C%22sq%22%3Atrue%2C%22lc%22%3A%22en-us%22%2C%22gat%22%3A%22u%22%2C%22gas%22%3A%22u%22%2C%22mo%22%3A%22u%22%2C%22r%22%3A%22u%22%2C%22c%22%3A%22u%22%2C%22t%22%3A%22u%22%2C%22i%22%3A%22u%22%2C%22cp_m%22%3A%22u%22%2C%22cp_is%22%3A%22u%22%2C%22cp_u%22%3A%22u%22%2C%22cp_t%22%3A%22u%22%2C%22sq_b%22%3A%22u%22%2C%22sq_e%22%3A%22u%22%2C%22sq_t%22%3A%22copy%22%2C%22ons%22%3A%22u%22%2C%22onl%22%3A%22u%22%7D&wc=%7B%22s%22%3Atrue%2C%22v%22%3A%22u%22%2C%22im%22%3A%22u%22%2C%22c%22%3Afalse%2C%22sp%22%3Afalse%2C%22af%22%3A%22u%22%2C%22stp%22%3Afalse%2C%22psp%22%3A%22u%22%2C%22e%22%3A%22u%22%2C%22mp%22%3A%22u%22%2C%22l%22%3A%22horizontal%22%2C%22co%22%3A%22none%22%2C%22b%22%3A%5B%7B%22id%22%3A%22googleplus%22%2C%22l%22%3A%22square%22%2C%22c%22%3Afalse%2C%22s%22%3A%22large%22%7D%2C%7B%22id%22%3A%22facebook%22%2C%22l%22%3A%22square%22%2C%22c%22%3Afalse%2C%22s%22%3A%22large%22%7D%2C%7B%22id%22%3A%22twitter%22%2C%22l%22%3A%22square%22%2C%22c%22%3Afalse%2C%22s%22%3A%22large%22%7D%2C%7B%22id%22%3A%22email%22%2C%22l%22%3A%22square%22%2C%22c%22%3Afalse%2C%22s%22%3A%22large%22%7D%2C%7B%22id%22%3A%22post%22%2C%22l%22%3A%22square%22%2C%22c%22%3Afalse%2C%22s%22%3A%22large%22%7D%5D%2C%22ev%22%3A%7B%22ons%22%3A%22u%22%2C%22onbc%22%3A%22u%22%2C%22onha%22%3A%22u%22%2C%22onsa%22%3A%22u%22%7D%2C%22ast%22%3A%22u%22%2C%22sa%22%3Atrue%2C%22d%22%3A%22u%22%2C%22trs%22%3A%22u%22%2C%22trt%22%3Atrue%7D&vGUID=eb21-7455-4c61-0704-28e2-a170-b763-17ef&random=1502703982222",
      "id": 4053,
      "contextId": 326,
      "parentContextId": -1,
      "windowId": 1,
      "start": 1502703982512,
      "end": 1502703982512,
      "requestHeaders": [
        {
          "name": "User-Agent",
          "value": "Mozilla/5.0 (X11; Linux x86_64) AppleWebKit/537.36 (KHTML, like Gecko) Chrome/60.0.3112.90 Safari/537.36"
        },
        {
          "name": "Accept",
          "value": "image/webp,image/apng,image/*,*/*;q=0.8"
        },
        {
          "name": "Referer",
          "value": "https://ebookee.org/"
        },
        {
          "name": "Accept-Encoding",
          "value": "gzip, deflate, br"
        },
        {
          "name": "Accept-Language",
          "value": "en-GB,en-US;q=0.8,en;q=0.6"
        },
        {
          "name": "Cookie",
          "value": "post_dcm=17392; post_uuid=27919174-8174-4091-a6a8-95b9da1c898f"
        }
      ]
    }
  },
  {
    "type": "response",
    "details": {
      "frameId": 0,
      "method": "GET",
      "parentFrameId": -1,
      "requestId": "3902",
      "responseHeaders": [
        {
          "name": "Content-Length",
          "value": "43"
        },
        {
          "name": "Server",
          "value": "cayman/1.0"
        },
        {
          "name": "Pragma",
          "value": "no-cache"
        },
        {
          "name": "Content-type",
          "value": "image/gif"
        },
        {
          "name": "Expires",
          "value": "Tue, 29 Oct 2002 19:50:44 GMT"
        },
        {
          "name": "Cache-control",
          "value": "private, no-cache, proxy-revalidate"
        },
        {
          "name": "Connection",
          "value": "close"
        }
      ],
      "statusCode": 200,
      "statusLine": "HTTP/1.1 200 OK",
      "tabId": 2,
      "type": "image",
      "url": "https://p.po.st/p?t=view&pub=https%3A%2F%2Febookee.org-498&pu=https%3A%2F%2Febookee.org%2F&pt=Ebookee%3A%20Free%20Download%20eBooks%20Search%20Engine!&ru=&vw=3&v=4.32.2-pch-1126&bs=30.sl%2C01.sl%2C02.sl%2C03.sl%2C999.sl&wv=2.1&gc=%7B%22tab%22%3A%22u%22%2C%22cp%22%3A%22u%22%2C%22sq%22%3Atrue%2C%22lc%22%3A%22en-us%22%2C%22gat%22%3A%22u%22%2C%22gas%22%3A%22u%22%2C%22mo%22%3A%22u%22%2C%22r%22%3A%22u%22%2C%22c%22%3A%22u%22%2C%22t%22%3A%22u%22%2C%22i%22%3A%22u%22%2C%22cp_m%22%3A%22u%22%2C%22cp_is%22%3A%22u%22%2C%22cp_u%22%3A%22u%22%2C%22cp_t%22%3A%22u%22%2C%22sq_b%22%3A%22u%22%2C%22sq_e%22%3A%22u%22%2C%22sq_t%22%3A%22copy%22%2C%22ons%22%3A%22u%22%2C%22onl%22%3A%22u%22%7D&wc=%7B%22s%22%3Atrue%2C%22v%22%3A%22u%22%2C%22im%22%3A%22u%22%2C%22c%22%3Afalse%2C%22sp%22%3Afalse%2C%22af%22%3A%22u%22%2C%22stp%22%3Afalse%2C%22psp%22%3A%22u%22%2C%22e%22%3A%22u%22%2C%22mp%22%3A%22u%22%2C%22l%22%3A%22horizontal%22%2C%22co%22%3A%22none%22%2C%22b%22%3A%5B%7B%22id%22%3A%22googleplus%22%2C%22l%22%3A%22square%22%2C%22c%22%3Afalse%2C%22s%22%3A%22large%22%7D%2C%7B%22id%22%3A%22facebook%22%2C%22l%22%3A%22square%22%2C%22c%22%3Afalse%2C%22s%22%3A%22large%22%7D%2C%7B%22id%22%3A%22twitter%22%2C%22l%22%3A%22square%22%2C%22c%22%3Afalse%2C%22s%22%3A%22large%22%7D%2C%7B%22id%22%3A%22email%22%2C%22l%22%3A%22square%22%2C%22c%22%3Afalse%2C%22s%22%3A%22large%22%7D%2C%7B%22id%22%3A%22post%22%2C%22l%22%3A%22square%22%2C%22c%22%3Afalse%2C%22s%22%3A%22large%22%7D%5D%2C%22ev%22%3A%7B%22ons%22%3A%22u%22%2C%22onbc%22%3A%22u%22%2C%22onha%22%3A%22u%22%2C%22onsa%22%3A%22u%22%7D%2C%22ast%22%3A%22u%22%2C%22sa%22%3Atrue%2C%22d%22%3A%22u%22%2C%22trs%22%3A%22u%22%2C%22trt%22%3Atrue%7D&vGUID=eb21-7455-4c61-0704-28e2-a170-b763-17ef&random=1502703982222",
      "id": 4053,
      "contextId": 326,
      "parentContextId": -1,
      "windowId": 1,
      "start": 1502703982546,
      "end": 1502703982552,
      "fromCache": false,
      "ip": "208.146.36.215"
    }
  },
  {
    "type": "navigation.completed",
    "details": {
      "frameId": 0,
      "processId": 47,
      "tabId": 2,
      "timeStamp": 1502703982553,
      "url": "https://ebookee.org/",
      "windowId": 1
    }
  },
  {
    "type": "tab.updated",
    "details": {
      "params": {
        "0": 2,
        "1": {
          "status": "complete"
        },
        "2": {
          "active": true,
          "audible": false,
          "autoDiscardable": true,
          "discarded": false,
          "height": 838,
          "highlighted": true,
          "id": 2,
          "incognito": false,
          "index": 0,
          "mutedInfo": {
            "muted": false
          },
          "pinned": false,
          "selected": true,
          "status": "complete",
          "title": "Ebookee: Free Download eBooks Search Engine!",
          "url": "https://ebookee.org/",
          "width": 935,
          "windowId": 1
        }
      },
      "timeStamp": 1502703982553
    }
  },
  {
    "type": "request",
    "details": {
      "frameId": 0,
      "method": "GET",
      "parentFrameId": -1,
      "requestId": "3903",
      "tabId": 2,
      "type": "image",
      "url": "https://ebookee.org/favicon.ico",
      "id": 4054,
      "contextId": 326,
      "parentContextId": -1,
      "windowId": 1,
      "start": 1502703982553,
      "end": 1502703982554,
      "requestHeaders": [
        {
          "name": "User-Agent",
          "value": "Mozilla/5.0 (X11; Linux x86_64) AppleWebKit/537.36 (KHTML, like Gecko) Chrome/60.0.3112.90 Safari/537.36"
        },
        {
          "name": "Accept",
          "value": "image/webp,image/apng,image/*,*/*;q=0.8"
        },
        {
          "name": "Referer",
          "value": "https://ebookee.org/"
        },
        {
          "name": "Accept-Encoding",
          "value": "gzip, deflate, br"
        },
        {
          "name": "Accept-Language",
          "value": "en-GB,en-US;q=0.8,en;q=0.6"
        },
        {
          "name": "Cookie",
          "value": "vs=0; __utmt=1; __utma=246647376.1276404275.1502703982.1502703982.1502703982.1; __utmb=246647376.1.10.1502703982; __utmc=246647376; __utmz=246647376.1502703982.1.1.utmcsr=(direct)|utmccn=(direct)|utmcmd=(none)"
        }
      ]
    }
  },
  {
    "type": "response",
    "details": {
      "frameId": 0,
      "method": "GET",
      "parentFrameId": -1,
      "requestId": "3903",
      "responseHeaders": [
        {
          "name": "status",
          "value": "200"
        },
        {
          "name": "server",
          "value": "nginx"
        },
        {
          "name": "date",
          "value": "Mon, 14 Aug 2017 09:46:22 GMT"
        },
        {
          "name": "content-type",
          "value": "image/x-icon"
        },
        {
          "name": "content-length",
          "value": "894"
        },
        {
          "name": "last-modified",
          "value": "Sat, 18 Feb 2017 18:33:23 GMT"
        },
        {
          "name": "etag",
          "value": "\"58a89373-37e\""
        },
        {
          "name": "expires",
          "value": "Wed, 13 Sep 2017 09:46:22 GMT"
        },
        {
          "name": "cache-control",
          "value": "max-age=2592000"
        },
        {
          "name": "accept-ranges",
          "value": "bytes"
        }
      ],
      "statusCode": 200,
      "statusLine": "HTTP/1.1 200",
      "tabId": 2,
      "type": "image",
      "url": "https://ebookee.org/favicon.ico",
      "id": 4054,
      "contextId": 326,
      "parentContextId": -1,
      "windowId": 1,
      "start": 1502703982563,
      "end": 1502703982564,
      "fromCache": false,
      "ip": "185.7.34.123"
    }
  },
  {
    "type": "tab.updated",
    "details": {
      "params": {
        "0": 2,
        "1": {
          "favIconUrl": "https://ebookee.org/favicon.ico"
        },
        "2": {
          "active": true,
          "audible": false,
          "autoDiscardable": true,
          "discarded": false,
          "favIconUrl": "https://ebookee.org/favicon.ico",
          "height": 838,
          "highlighted": true,
          "id": 2,
          "incognito": false,
          "index": 0,
          "mutedInfo": {
            "muted": false
          },
          "pinned": false,
          "selected": true,
          "status": "complete",
          "title": "Ebookee: Free Download eBooks Search Engine!",
          "url": "https://ebookee.org/",
          "width": 935,
          "windowId": 1
        }
      },
      "timeStamp": 1502703982564
    }
  },
  {
    "type": "request",
    "details": {
      "frameId": 0,
      "method": "GET",
      "parentFrameId": -1,
      "requestId": "3904",
      "tabId": 2,
      "type": "main_frame",
      "url": "chrome-extension://ikfgdchohmenjhbbpbnknidjagelhjma/command.html?save",
      "id": 4055,
      "contextId": 327,
      "parentContextId": -1,
      "windowId": 1,
      "start": 1502703983599,
      "end": 1502703983599
    }
  },
  {
    "type": "response",
    "details": {
      "frameId": 0,
      "fromCache": false,
      "method": "GET",
      "parentFrameId": -1,
      "requestId": "3904",
      "responseHeaders": [
        {
          "name": "Content-Security-Policy",
          "value": "script-src 'self' blob: filesystem: chrome-extension-resource:; object-src 'self' blob: filesystem:;"
        },
        {
          "name": "ETag",
          "value": "\"03Ernejg3qv7y3J6F/ZJ7VWrBX4=\""
        },
        {
          "name": "cache-control",
          "value": "no-cache"
        }
      ],
      "statusCode": 200,
      "statusLine": "HTTP/1.1 200 OK",
      "tabId": 2,
      "type": "main_frame",
      "url": "chrome-extension://ikfgdchohmenjhbbpbnknidjagelhjma/command.html?save",
      "id": 4055,
      "contextId": 327,
      "parentContextId": -1,
      "windowId": 1,
      "start": 1502703983599,
      "end": 1502703983605
    }
  },
  {
    "type": "tab.updated",
    "details": {
      "params": {
        "0": 2,
        "1": {
          "status": "loading",
          "url": "chrome-extension://ikfgdchohmenjhbbpbnknidjagelhjma/command.html?save"
        },
        "2": {
          "active": true,
          "audible": false,
          "autoDiscardable": true,
          "discarded": false,
          "height": 838,
          "highlighted": true,
          "id": 2,
          "incognito": false,
          "index": 0,
          "mutedInfo": {
            "muted": false
          },
          "pinned": false,
          "selected": true,
          "status": "loading",
          "title": "chrome-extension://ikfgdchohmenjhbbpbnknidjagelhjma/command.html?save",
          "url": "chrome-extension://ikfgdchohmenjhbbpbnknidjagelhjma/command.html?save",
          "width": 935,
          "windowId": 1
        }
      },
      "timeStamp": 1502703983605
    }
  },
  {
    "type": "tab.zoomChange",
    "details": {
      "params": {
        "0": {
          "newZoomFactor": 1,
          "oldZoomFactor": 1,
          "tabId": 2,
          "zoomSettings": {
            "mode": "automatic",
            "scope": "per-origin"
          }
        }
      },
      "timeStamp": 1502703983605
    }
  },
  {
    "type": "navigation.committed",
    "details": {
      "frameId": 0,
      "processId": 4,
      "tabId": 2,
      "timeStamp": 1502703983605,
      "transitionQualifiers": [],
      "transitionType": "typed",
      "url": "chrome-extension://ikfgdchohmenjhbbpbnknidjagelhjma/command.html?save",
      "windowId": 1
    }
  },
  {
    "type": "download.visited",
    "details": {
      "params": {
        "0": {
          "id": "5",
          "lastVisitTime": 1502703983600.6838,
          "title": "Save",
          "typedCount": 41,
          "url": "chrome-extension://ikfgdchohmenjhbbpbnknidjagelhjma/command.html?save",
          "visitCount": 41
        }
      },
      "timeStamp": 1502703983607
    }
  },
  {
    "type": "request",
    "details": {
      "frameId": 0,
      "method": "GET",
      "parentFrameId": -1,
      "requestId": "3905",
      "tabId": 2,
      "type": "script",
      "url": "chrome-extension://ikfgdchohmenjhbbpbnknidjagelhjma/command.js",
      "id": 4056,
      "contextId": 327,
      "parentContextId": -1,
      "windowId": 1,
      "start": 1502703983608,
      "end": 1502703983608
    }
  },
  {
    "type": "tab.updated",
    "details": {
      "params": {
        "0": 2,
        "1": {
          "title": "Save"
        },
        "2": {
          "active": true,
          "audible": false,
          "autoDiscardable": true,
          "discarded": false,
          "favIconUrl": "",
          "height": 838,
          "highlighted": true,
          "id": 2,
          "incognito": false,
          "index": 0,
          "mutedInfo": {
            "muted": false
          },
          "pinned": false,
          "selected": true,
          "status": "loading",
          "title": "Save",
          "url": "chrome-extension://ikfgdchohmenjhbbpbnknidjagelhjma/command.html?save",
          "width": 935,
          "windowId": 1
        }
      },
      "timeStamp": 1502703983608
    }
  },
  {
    "type": "response",
    "details": {
      "frameId": 0,
      "fromCache": false,
      "method": "GET",
      "parentFrameId": -1,
      "requestId": "3905",
      "responseHeaders": [
        {
          "name": "Content-Security-Policy",
          "value": "script-src 'self' blob: filesystem: chrome-extension-resource:; object-src 'self' blob: filesystem:;"
        },
        {
          "name": "ETag",
          "value": "\"jz1CzBTntdxSx6wasmgnFiA6bUw=\""
        },
        {
          "name": "cache-control",
          "value": "no-cache"
        }
      ],
      "statusCode": 200,
      "statusLine": "HTTP/1.1 200 OK",
      "tabId": 2,
      "type": "script",
      "url": "chrome-extension://ikfgdchohmenjhbbpbnknidjagelhjma/command.js",
      "id": 4056,
      "contextId": 327,
      "parentContextId": -1,
      "windowId": 1,
      "start": 1502703983608,
      "end": 1502703983608
    }
  }
]